{
  "report_name": "RPT_NEEQ_ISSUEINFO_LIST",
  "success": true,
  "message": "ok",
  "fields": [
    "ORG_CODE",
    "SECURITY_CODE",
    "SECUCODE",
    "SECURITY_NAME_ABBR",
    "APPLY_CODE",
    "EXPECT_ISSUE_NUM",
    "PRICE_WAY",
    "ISSUE_PRICE",
    "ISSUE_PE_RATIO",
    "APPLY_DATE",
    "RESULT_NOTICE_DATE",
    "SELECT_LISTING_DATE",
    "ONLINE_ISSUE_NUM",
    "APPLY_AMT_UPPER",
    "APPLY_NUM_UPPER",
    "ONLINE_PAY_DATE",
    "ONLINE_REFUND_DATE",
    "INFO_CODE",
    "ONLINE_ISSUE_LWR",
    "NEWEST_PRICE",
    "CLOSE_PRICE",
    "INITIAL_MULTIPLE",
    "PER_SHARES_INCOME",
    "LD_CLOSE_CHANGE",
    "TURNOVERRATE",
    "AMPLITUDE",
    "ONLINE_APPLY_LOWER",
    "MAIN_BUSINESS",
    "INDUSTRY_PE_RATIO",
    "APPLY_AMT_100",
    "TAKE_UP_TIME",
    "CAPTURE_PROFIT",
    "APPLY_SHARE_100",
    "AVERAGE_PRICE",
    "ORG_VAN",
    "VA_AMT",
    "ISSUE_PRICE_ADJFACTOR",
    "FRIST_CLOSE_CHANGE",
    "LISTING_STATE"
  ],
  "sample": [
    {
      "ORG_CODE": "10912976",
      "SECURITY_CODE": "920096",
      "SECUCODE": "920096.BJ",
      "SECURITY_NAME_ABBR": "嘉晨智能",
      "APPLY_CODE": "920096",
      "EXPECT_ISSUE_NUM": 18000000,
      "PRICE_WAY": "直接定价",
      "ISSUE_PRICE": 14.43,
      "ISSUE_PE_RATIO": 14.99,
      "APPLY_DATE": "2026-05-06 00:00:00",
      "RESULT_NOTICE_DATE": "2026-05-11 00:00:00",
      "SELECT_LISTING_DATE": "2026-05-18 00:00:00",
      "ONLINE_ISSUE_NUM": 16200000,
      "APPLY_AMT_UPPER": 11688300,
      "APPLY_NUM_UPPER": 810000,
      "ONLINE_PAY_DATE": "2026-05-06 00:00:00",
      "ONLINE_REFUND_DATE": "2026-05-08 00:00:00",
      "INFO_CODE": "AN202604291821742488",
      "ONLINE_ISSUE_LWR": 0.02679695,
      "NEWEST_PRICE": 66.68,
      "CLOSE_PRICE": 112.01,
      "INITIAL_MULTIPLE": null,
      "PER_SHARES_INCOME": 6502.65,
      "LD_CLOSE_CHANGE": 450.634095634096,
      "TURNOVERRATE": 94.9896,
      "AMPLITUDE": 291.1296,
      "ONLINE_APPLY_LOWER": 100,
      "MAIN_BUSINESS": "电气控制系统产品及整体解决方案的研发、生产和销售",
      "INDUSTRY_PE_RATIO": 43.79,
      "APPLY_AMT_100": 5385000,
      "TAKE_UP_TIME": 3,
      "CAPTURE_PROFIT": 14.691843082637,
      "APPLY_SHARE_100": 373200,
      "AVERAGE_PRICE": 79.4565,
      "ORG_VAN": 502296,
      "VA_AMT": 872360419125,
      "ISSUE_PRICE_ADJFACTOR": 14.43,
      "FRIST_CLOSE_CHANGE": 676.230076230076,
      "LISTING_STATE": "0"
    },
    {
      "ORG_CODE": "10000246700",
      "SECURITY_CODE": "920160",
      "SECUCODE": "920160.BJ",
      "SECURITY_NAME_ABBR": "北矿检测",
      "APPLY_CODE": "920160",
      "EXPECT_ISSUE_NUM": 28320000,
      "PRICE_WAY": "直接定价",
      "ISSUE_PRICE": 6.7,
      "ISSUE_PE_RATIO": 14.99,
      "APPLY_DATE": "2025-11-03 00:00:00",
      "RESULT_NOTICE_DATE": "2025-11-06 00:00:00",
      "SELECT_LISTING_DATE": "2025-11-18 00:00:00",
      "ONLINE_ISSUE_NUM": 25488000,
      "APPLY_AMT_UPPER": 8538480,
      "APPLY_NUM_UPPER": 1274400,
      "ONLINE_PAY_DATE": "2025-11-03 00:00:00",
      "ONLINE_REFUND_DATE": "2025-11-05 00:00:00",
      "INFO_CODE": "AN202510301772029276",
      "ONLINE_ISSUE_LWR": 0.02273565,
      "NEWEST_PRICE": 21.33,
      "CLOSE_PRICE": 26.5,
      "INITIAL_MULTIPLE": null,
      "PER_SHARES_INCOME": 2258.91,
      "LD_CLOSE_CHANGE": 337.150746268657,
      "TURNOVERRATE": 88.4608,
      "AMPLITUDE": 83.5821,
      "ONLINE_APPLY_LOWER": 100,
      "MAIN_BUSINESS": "检验检测业务以及检测仪器的研发、生产、销售和技术服务",
      "INDUSTRY_PE_RATIO": 38.77,
      "APPLY_AMT_100": 2947000,
      "TAKE_UP_TIME": 3,
      "CAPTURE_PROFIT": 9.325892432983,
      "APPLY_SHARE_100": 439900,
      "AVERAGE_PRICE": 29.2891,
      "ORG_VAN": 591485,
      "VA_AMT": 751109546750,
      "ISSUE_PRICE_ADJFACTOR": 6.7,
      "FRIST_CLOSE_CHANGE": 295.522388059701,
      "LISTING_STATE": "0"
    }
  ]
}